local/__init__.py
silas/__init__.py
silas/base.py
silas/enumerate.py
silas/env.py
silas/error.py
silas/file.py
silas/yml.py
silas/files/__init__.py
silas/files/yml.py
silas-1.0.0.dist-info/LICENSE
silas-1.0.0.dist-info/METADATA
silas-1.0.0.dist-info/WHEEL
silas-1.0.0.dist-info/top_level.txt
silas-1.0.0.dist-info/RECORD
