Metadata-Version: 2.1
Name: silas
Version: 1.0.0
Summary: Fast and convenient configuration reading.
Home-page: https://github.com/xccx0823/silas
Author: XChao
Author-email: cheerxiong0823@163.com
License: UNKNOWN
Platform: UNKNOWN
Classifier: Development Status :: 5 - Production/Stable
Classifier: Intended Audience :: Developers
Classifier: Natural Language :: English
Classifier: Programming Language :: Python
Classifier: Programming Language :: Python :: 3
Classifier: Programming Language :: Python :: 3.6
Classifier: Programming Language :: Python :: 3.7
Classifier: Programming Language :: Python :: Implementation :: CPython
Requires-Python: >=3.6
License-File: LICENSE
Requires-Dist: PyYAML (==6.0)
